llm_app/__init__.py
llm_app/model_wrappers/__init__.py
llm_app/model_wrappers/api_clients/__init__.py
llm_app/model_wrappers/api_clients/clients.py
llm_app/model_wrappers/base.py
llm_app/model_wrappers/huggingface_wrapper/api_models.py
llm_app/model_wrappers/huggingface_wrapper/pipelines.py
llm_app/model_wrappers/litellm_wrapper/__init__.py
llm_app/model_wrappers/litellm_wrapper/api_models.py
llm_app/model_wrappers/openai_wrapper/__init__.py
llm_app/model_wrappers/openai_wrapper/api_models.py
llm_app/model_wrappers/sentence_transformer/embedding.py
llm_app/processing.py
llm_app/utils.py
llm_app-0.3.6.dist-info/LICENSE
llm_app-0.3.6.dist-info/METADATA
llm_app-0.3.6.dist-info/WHEEL
llm_app-0.3.6.dist-info/RECORD
