Metadata-Version: 2.1
Name: llm-app
Version: 0.3.6
Summary: LLM-App is a library for creating responsive AI applications leveraging OpenAI/Hugging Face APIs to provide responses to user queries based on live data sources. Build your own LLM application in 30 lines of code, no vector database required.
License: MIT
Keywords: Pathway,LLM
Author: Jan Chorowski
Author-email: janek@pathway.com
Requires-Python: >=3.10,<3.13
Classifier: Development Status :: 3 - Alpha
Classifier: Intended Audience :: Developers
Classifier: License :: OSI Approved :: MIT License
Classifier: Programming Language :: Python :: 3
Classifier: Programming Language :: Python :: 3.10
Classifier: Programming Language :: Python :: 3.11
Classifier: Programming Language :: Python :: 3.12
Classifier: Programming Language :: Python :: Implementation :: CPython
Provides-Extra: local
Provides-Extra: unstructured
Provides-Extra: unstructured-to-sql
Requires-Dist: diskcache (>=5.6.1,<6.0.0)
Requires-Dist: openai (>=1.2.4)
Requires-Dist: pathway (==0.7.7)
Requires-Dist: psycopg (>=3.1.12,<4.0.0) ; extra == "unstructured-to-sql"
Requires-Dist: requests (>=2.31.0,<3.0.0)
Requires-Dist: sentence-transformers (>=2.2.2,<3.0.0) ; extra == "local"
Requires-Dist: streamlit (>=1.26.0,<2.0.0)
Requires-Dist: tiktoken (>=0.5.1,<0.6.0) ; extra == "unstructured" or extra == "unstructured-to-sql"
Requires-Dist: torch (>=2.0.0,!=2.0.1) ; extra == "local"
Requires-Dist: unstructured[all-docs] (>=0.10.15,<0.11.0) ; extra == "unstructured" or extra == "unstructured-to-sql"
Project-URL: Homepage, https://github.com/pathwaycom/llm-app
Project-URL: Source Code, https://github.com/pathwaycom/llm-app
